llumnix/__init__.py
llumnix/arg_utils.py
llumnix/config.py
llumnix/instance_info.py
llumnix/llm_engine_manager.py
llumnix/logger.py
llumnix/server_info.py
llumnix/utils.py
llumnix/version.py
llumnix/backends/__init__.py
llumnix/backends/backend_interface.py
llumnix/backends/migration_backend_interface.py
llumnix/backends/profiling.py
llumnix/backends/utils.py
llumnix/backends/vllm/__init__.py
llumnix/backends/vllm/executor.py
llumnix/backends/vllm/llm_engine.py
llumnix/backends/vllm/migration_backend.py
llumnix/backends/vllm/scheduler.py
llumnix/backends/vllm/simulator.py
llumnix/backends/vllm/utils.py
llumnix/backends/vllm/worker.py
llumnix/entrypoints/__init__.py
llumnix/entrypoints/llumnix_utils.py
llumnix/entrypoints/vllm/__init__.py
llumnix/entrypoints/vllm/api_server.py
llumnix/global_scheduler/__init__.py
llumnix/global_scheduler/dispatch_scheduler.py
llumnix/global_scheduler/global_scheduler.py
llumnix/global_scheduler/migration_scheduler.py
llumnix/global_scheduler/scaling_scheduler.py
llumnix/llumlet/__init__.py
llumnix/llumlet/llumlet.py
llumnix/llumlet/local_migration_scheduler.py
llumnix/llumlet/migrating_request.py
llumnix/llumlet/migration_coordinator.py
tests/__init__.py
tests/backends/__init__.py
tests/backends/vllm/__init__.py
tests/backends/vllm/test_llm_engine.py
tests/backends/vllm/test_migration.py
tests/backends/vllm/test_migration_backend.py
tests/backends/vllm/test_scheduler.py
tests/backends/vllm/test_worker.py
tests/backends/vllm/utils.py
tests/entrypoints/__init__.py
tests/entrypoints/test_llumnix_utils.py
tests/entrypoints/vllm/__init__.py
tests/entrypoints/vllm/api_server_manager.py
tests/entrypoints/vllm/test_api_server.py
tests/global_scheduler/__init__.py
tests/global_scheduler/test_dispatch_scheduler.py
tests/global_scheduler/test_global_scheduler.py
tests/global_scheduler/test_llm_engine_manager.py
tests/global_scheduler/test_migration_scheduler.py
tests/llumlet/__init__.py
tests/llumlet/test_migration_coordinator.py
llumnix-0.0.2.dist-info/LICENSE
llumnix-0.0.2.dist-info/METADATA
llumnix-0.0.2.dist-info/WHEEL
llumnix-0.0.2.dist-info/top_level.txt
llumnix-0.0.2.dist-info/RECORD
