Metadata-Version: 2.1
Name: llumnix
Version: 0.0.2
Summary: Efficient and easy multi-instance LLM serving
Home-page: https://github.com/AlibabaPAI/llumnix
Author: Llumnix Team
License: Apache 2.0
Platform: all
Classifier: Programming Language :: Python
Classifier: Programming Language :: Python :: 3.8
Classifier: Programming Language :: Python :: 3.9
Classifier: Programming Language :: Python :: 3.10
Classifier: License :: OSI Approved :: Apache Software License
Classifier: Topic :: Scientific/Engineering :: Artificial Intelligence
Requires-Python: >=3.8.1, <3.11
License-File: LICENSE
Requires-Dist: vllm ==0.4.2
Requires-Dist: ray >=2.9.0
Requires-Dist: pyarrow
Requires-Dist: aiohttp
Requires-Dist: scipy
Requires-Dist: pandas
Requires-Dist: matplotlib
Requires-Dist: func-timeout
Requires-Dist: numpy <1.24.0
